chaincraft_cli.py
chaincraft/__init__.py
chaincraft/index_helper.py
chaincraft/node.py
chaincraft/shared_message.py
chaincraft/shared_object.py
chaincraft/crypto_primitives/__init__.py
chaincraft/crypto_primitives/abstract.py
chaincraft/crypto_primitives/address.py
chaincraft/crypto_primitives/encrypt.py
chaincraft/crypto_primitives/pow.py
chaincraft/crypto_primitives/sign.py
chaincraft/crypto_primitives/vdf.py
chaincraft/crypto_primitives/vrf.py
chaincraft-0.4.1.dist-info/licenses/LICENSE
examples/__init__.py
examples/blockchain.md
examples/blockchain.py
examples/chatroom.md
examples/chatroom_cli.py
examples/chatroom_protocol.py
examples/randomness_beacon.py
examples/tendermint.md
examples/tendermint_bft.py
examples/tendermint_cli.py
chaincraft-0.4.1.dist-info/METADATA
chaincraft-0.4.1.dist-info/WHEEL
chaincraft-0.4.1.dist-info/entry_points.txt
chaincraft-0.4.1.dist-info/top_level.txt
chaincraft-0.4.1.dist-info/RECORD
