Metadata-Version: 2.4
Name: chaincraft
Version: 0.4.1
Summary: A platform for blockchain education and prototyping
Author-email: Chaincraft Contributors <chaincraft@example.com>
Maintainer-email: Chaincraft Contributors <chaincraft@example.com>
License: MIT
Project-URL: Homepage, https://github.com/jio-gl/chaincraft
Project-URL: Repository, https://github.com/jio-gl/chaincraft
Project-URL: Documentation, https://github.com/jio-gl/chaincraft#readme
Project-URL: Bug Tracker, https://github.com/jio-gl/chaincraft/issues
Keywords: blockchain,education,prototyping,distributed,consensus
Classifier: Development Status :: 3 - Alpha
Classifier: Intended Audience :: Education
Classifier: Intended Audience :: Developers
Classifier: Operating System :: OS Independent
Classifier: Programming Language :: Python :: 3
Classifier: Programming Language :: Python :: 3.8
Classifier: Programming Language :: Python :: 3.9
Classifier: Programming Language :: Python :: 3.10
Classifier: Programming Language :: Python :: 3.11
Classifier: Programming Language :: Python :: 3.12
Classifier: Topic :: Education
Classifier: Topic :: Software Development :: Libraries :: Python Modules
Classifier: Topic :: System :: Distributed Computing
Requires-Python: >=3.8
License-File: LICENSE
Requires-Dist: cryptography>=44.0.1
Provides-Extra: dev
Requires-Dist: pytest>=6.0; extra == "dev"
Requires-Dist: flake8>=3.8.0; extra == "dev"
Requires-Dist: black>=21.0.0; extra == "dev"
Requires-Dist: mypy>=0.910; extra == "dev"
Dynamic: license-file
